tickinfo/__init__.py
tickinfo/tickinfo.py
tickinfo-0.1.1.dist-info/METADATA
tickinfo-0.1.1.dist-info/WHEEL
tickinfo-0.1.1.dist-info/top_level.txt
tickinfo-0.1.1.dist-info/RECORD
