Metadata-Version: 2.1
Name: tickinfo
Version: 0.1.1
Summary: get ticker data and create SMA plot
Home-page: http://github.com/ivanpuzako/tickinfo.git
Author: Ivanpuzako
Author-email: Ivanpuzako@gmail.com
License: MIT
Platform: UNKNOWN
Requires-Dist: matplotlib
Requires-Dist: pandas
Requires-Dist: yfinance
